{
    "signin": {
        "title": "Sign in",
        "image": "images/signin.jpg",
        "links": [
            {
                "href": "signup",
                "x": 45,
                "y": 488,
                "width": 135,
                "height": 56
            },
            {
                "href": "dashboard",
                "x": 185,
                "y": 487,
                "width": 141,
                "height": 57
            }
        ]
    },
    "signup": {
        "title": "Sign up",
        "image": "images/signup.jpg",
        "links": [
            {
                "href": "dashboard",
                "x": 18,
                "y": 606,
                "width": 324,
                "height": 32
            }
        ]
    },
    "dashboard": {
        "title": "Dashboard",
        "image": "images/dashboard.jpg",
        "links": [
            {
                "href": "menu",
                "x": 32,
                "y": 83,
                "width": 42,
                "height": 42
            }
        ]
    },
    "menu": {
        "title": "Menu",
        "image": "images/menu.jpg",
        "links": [
            {
                "href": "dashboard",
                "x": 22,
                "y": 196,
                "width": 237,
                "height": 58
            },
            {
                "href": "buddy",
                "x": 22,
                "y": 263,
                "width": 237,
                "height": 66
            },
            {
                "href": "tracking",
                "x": 22,
                "y": 332,
                "width": 237,
                "height": 62
            },
            {
                "href": "challenge",
                "x": 22,
                "y": 397,
                "width": 237,
                "height": 61
            },
            {
                "href": "event",
                "x": 22,
                "y": 516,
                "width": 235,
                "height": 55
            },
            {
                "href": "recipe",
                "x": 22,
                "y": 576,
                "width": 234,
                "height": 41
            }
        ]
    },
    "qr_code": {
        "title": "QR Code",
        "image": "images/qr_code.jpg",
        "links": [
            {
                "href": "menu",
                "x": 35,
                "y": 79,
                "width": 33,
                "height": 25
            }
        ]
    },
    "buddy": {
        "title": "Buddy",
        "image": "images/buddy_empty.jpg",
        "links": [
            {
                "href": "menu",
                "x": 35,
                "y": 79,
                "width": 38,
                "height": 39
            },
            {
                "href": "buddy_form",
                "x": 18,
                "y": 563,
                "width": 324,
                "height": 75
            }
        ]
    },
    "buddy_form": {
        "title": "Buddy search form",
        "image": "images/buddy_form.jpg",
        "links": [
            {
                "href": "buddy",
                "x": 30,
                "y": 75,
                "width": 43,
                "height": 43
            },
            {
                "href": "buddy_detail",
                "x": 30,
                "y": 469,
                "width": 305,
                "height": 30
            }
        ]
    },
    "buddy_detail": {
        "title": "Buddy profile",
        "image": "images/buddy_detail.jpg",
        "links": [
            {
                "href": "menu",
                "x": 35,
                "y": 79,
                "width": 33,
                "height": 29
            },
            {
                "href": "buddy_message",
                "x": 254,
                "y": 551,
                "width": 70,
                "height": 74
            }
        ]
    },
    "buddy_message": {
        "title": "Buddy message",
        "image": "images/buddy_message.jpg",
        "links": [
            {
                "href": "buddy_detail",
                "x": 31,
                "y": 83,
                "width": 37,
                "height": 31
            },
            {
                "href": "buddy_share",
                "x": 26,
                "y": 590,
                "width": 30,
                "height": 44
            }
        ]
    },
    "buddy_share": {
        "title": "Buddy share",
        "image": "images/buddy_share.jpg",
        "links": [
            {
                "href": "buddy_message",
                "x": 36,
                "y": 85,
                "width": 43,
                "height": 33
            },
            {
                "href": "buddy_message",
                "x": 60,
                "y": 651,
                "width": 27,
                "height": 32
            }
        ]
    },
    "challenge": {
        "title": "Challenge",
        "image": "images/challenge.jpg",
        "links": [
            {
                "href": "menu",
                "x": 41,
                "y": 83,
                "width": 29,
                "height": 35
            },
            {
                "href": "challenge_detail",
                "x": 35,
                "y": 283,
                "width": 297,
                "height": 38
            }
        ]
    },
    "challenge_detail": {
        "title": "Challenge detail",
        "image": "images/challenge_detail.jpg",
        "links": [
            {
                "href": "challenge",
                "x": 57,
                "y": 656,
                "width": 27,
                "height": 27
            },
            {
                "href": "challenge",
                "x": 36,
                "y": 458,
                "width": 144,
                "height": 78
            },
            {
                "href": "challenge",
                "x": 186,
                "y": 459,
                "width": 141,
                "height": 79
            }
        ]
    },
    "event": {
        "title": "Event",
        "image": "images/event.jpg",
        "links": [
            {
                "href": "menu",
                "x": 43,
                "y": 79,
                "width": 34,
                "height": 32
            },
            {
                "href": "event_detail",
                "x": 27,
                "y": 334,
                "width": 307,
                "height": 34
            }
        ]
    },
    "event_detail": {
        "title": "Event detail",
        "image": "images/event_detail.jpg",
        "links": [
            {
                "href": "event",
                "x": 37,
                "y": 83,
                "width": 35,
                "height": 31
            },
            {
                "href": "event",
                "x": 18,
                "y": 579,
                "width": 158,
                "height": 59
            },
            {
                "href": "event",
                "x": 183,
                "y": 579,
                "width": 160,
                "height": 59
            }
        ]
    },
    "recipe": {
        "title": "Recipe",
        "image": "images/recipe.jpg",
        "links": [
            {
                "href": "menu",
                "x": 39,
                "y": 79,
                "width": 34,
                "height": 35
            },
            {
                "href": "recipe_detail",
                "x": 31,
                "y": 170,
                "width": 298,
                "height": 170
            }
        ]
    },
    "recipe_detail": {
        "title": "Recipe detail",
        "image": "images/recipe_detail.jpg",
        "links": [
            {
                "href": "recipe",
                "x": 34,
                "y": 79,
                "width": 34,
                "height": 32
            },
            {
                "href": "recipe",
                "x": 46,
                "y": 353,
                "width": 276,
                "height": 35
            }
        ]
    },
    "tracking": {
        "title": "Tracking",
        "image": "images/tracking.jpg",
        "links": [
            {
                "href": "menu",
                "x": 38,
                "y": 79,
                "width": 43,
                "height": 35
            },
            {
                "href": "tracking_weight",
                "x": 32,
                "y": 173,
                "width": 305,
                "height": 105
            },
            {
                "href": "tracking_meal",
                "x": 32,
                "y": 286,
                "width": 305,
                "height": 102
            }
        ]
    },
    "tracking_weight": {
        "title": "Tracking weight",
        "image": "images/tracking_weight.jpg",
        "links": [
            {
                "href": "tracking",
                "x": 38,
                "y": 85,
                "width": 34,
                "height": 29
            },
            {
                "href": "tracking_weight_add",
                "x": 266,
                "y": 563,
                "width": 65,
                "height": 67
            }
        ]
    },
    "tracking_weight_add": {
        "title": "Tracking weight add",
        "image": "images/tracking_weight_add.jpg",
        "links": [
            {
                "href": "tracking_weight",
                "x": 40,
                "y": 431,
                "width": 283,
                "height": 55
            }
        ]
    },
    "tracking_meal": {
        "title": "Tracking meal",
        "image": "images/tracking_meal.jpg",
        "links": [
            {
                "href": "tracking",
                "x": 35,
                "y": 83,
                "width": 35,
                "height": 31
            },
            {
                "href": "tracking_meal_add",
                "x": 244,
                "y": 547,
                "width": 69,
                "height": 69
            }
        ]
    },
    "tracking_meal_add": {
        "title": "Tracking meal add",
        "image": "images/tracking_meal_add.jpg",
        "links": [
            {
                "href": "tracking_meal",
                "x": 38,
                "y": 85,
                "width": 36,
                "height": 26
            },
            {
                "href": "tracking_meal",
                "x": 18,
                "y": 582,
                "width": 326,
                "height": 59
            }
        ]
    }
}